TimetableToImage/__init__.py
TimetableToImage/Image/__init__.py
TimetableToImage/Image/func.py
TimetableToImage/Image/fonts/Golos-UI/font_bold.ttf
TimetableToImage/Image/fonts/Golos-UI/font_medium.ttf
TimetableToImage/Image/fonts/Golos-UI/font_regular.ttf
TimetableToImage/Timetable/__init__.py
TimetableToImage/Timetable/bell.py
TimetableToImage/Timetable/bells.py
TimetableToImage/Timetable/day.py
TimetableToImage/Timetable/func.py
TimetableToImage/Timetable/lesson.py
TimetableToImage/Timetable/pair.py
TimetableToImage/Timetable/week.py
timetable_to_image-1.2.1.dist-info/LICENSE
timetable_to_image-1.2.1.dist-info/METADATA
timetable_to_image-1.2.1.dist-info/WHEEL
timetable_to_image-1.2.1.dist-info/top_level.txt
timetable_to_image-1.2.1.dist-info/RECORD
