Metadata-Version: 2.1
Name: timetable-to-image
Version: 1.2.1
Summary: The Python library provides functionality for generating a timetable image from an object representation
Author-email: potapovns <ns.potapov73@gmail.com>
License: MIT License
Project-URL: Homepage, https://github.com/potapovns/timetable_to_image
Keywords: timetable,image
Classifier: License :: OSI Approved :: MIT License
Classifier: Programming Language :: Python
Classifier: Programming Language :: Python :: 3
Requires-Python: >=3.8
License-File: LICENSE
Requires-Dist: Pillow
Provides-Extra: dev
Requires-Dist: bumpver ; extra == 'dev'
Requires-Dist: pytest ; extra == 'dev'
